eachread/__init__.py
eachread/cli.py
eachread/wordnet/__init__.py
eachread/wordnet/adjanimal.py
eachread/wordnet/adjectives.py
eachread/wordnet/commands.py
eachread/wordnet/data.py
eachread/wordnet/display.py
eachread/wordnet/utils.py
eachread-0.1.2.dist-info/METADATA
eachread-0.1.2.dist-info/WHEEL
eachread-0.1.2.dist-info/entry_points.txt
eachread-0.1.2.dist-info/RECORD
