Metadata-Version: 2.4
Name: eachread
Version: 0.1.2
Summary: Add your description here
Author-email: Taylor Monacelli <taylormonacelli@gmail.com>
Requires-Python: ==3.12.0
Requires-Dist: nltk
